kubesdk/__init__.py
kubesdk/_auth.py
kubesdk/_temp_files.py
kubesdk/client.py
kubesdk/common.py
kubesdk/crd.py
kubesdk/credentials.py
kubesdk/errors.py
kubesdk/login.py
kubesdk/py.typed
kubesdk/_patch/__init__.py
kubesdk/_patch/json_patch.py
kubesdk/_patch/strategic_merge_patch.py
kubesdk/_path/__init__.py
kubesdk/_path/picker.py
kubesdk/_path/replace_at_path.py
kubesdk-0.3.3.dist-info/METADATA
kubesdk-0.3.3.dist-info/WHEEL
kubesdk-0.3.3.dist-info/RECORD
