Metadata-Version: 2.4
Name: kubesdk
Version: 0.3.3
Summary: Fast, fully typed Kubernetes client for Python.
Project-URL: Repository, https://github.com/puzl-cloud/kubesdk
Author-email: Nik Paushkin <nik@puzl.cloud>
License: MIT
Keywords: client,kubernetes,kubesdk
Classifier: Development Status :: 5 - Production/Stable
Classifier: Intended Audience :: Developers
Classifier: License :: OSI Approved :: MIT License
Classifier: Operating System :: OS Independent
Classifier: Programming Language :: Python
Classifier: Programming Language :: Python :: 3 :: Only
Classifier: Programming Language :: Python :: 3.10
Classifier: Programming Language :: Python :: 3.11
Classifier: Programming Language :: Python :: 3.12
Classifier: Programming Language :: Python :: 3.13
Classifier: Programming Language :: Python :: 3.14
Requires-Python: >=3.10
Requires-Dist: aiohttp==3.12.15
Requires-Dist: kube-models<1.0,>=0.4.1
Requires-Dist: pyyaml==6.0.3
Provides-Extra: cli
Requires-Dist: kubesdk-cli; extra == 'cli'
